README.rst
setup.py
aldryn_apphook_reload/__init__.py
aldryn_apphook_reload/admin.py
aldryn_apphook_reload/apps.py
aldryn_apphook_reload/compat.py
aldryn_apphook_reload/middleware.py
aldryn_apphook_reload/models.py
aldryn_apphook_reload/signals.py
aldryn_apphook_reload/tests.py
aldryn_apphook_reload/utils.py
aldryn_apphook_reload.egg-info/PKG-INFO
aldryn_apphook_reload.egg-info/SOURCES.txt
aldryn_apphook_reload.egg-info/dependency_links.txt
aldryn_apphook_reload.egg-info/not-zip-safe
aldryn_apphook_reload.egg-info/requires.txt
aldryn_apphook_reload.egg-info/top_level.txt
aldryn_apphook_reload/migrations/0001_initial.py
aldryn_apphook_reload/migrations/__init__.py
aldryn_apphook_reload/test_utils/__init__.py
aldryn_apphook_reload/test_utils/test_app/__init__.py
aldryn_apphook_reload/test_utils/test_app/cms_app.py
aldryn_apphook_reload/test_utils/test_app/test_reverse_urls.py
aldryn_apphook_reload/test_utils/test_app/urls.py