Metadata-Version: 1.1
Name: aldryn-apphook-reload
Version: 0.3.0
Summary: Reload urls of django CMS Apphooks without a restart
Home-page: https://github.com/aldryn/aldryn-apphook-reload/
Author: Stefan Foulis
Author-email: stefan@foulis.ch
License: BSD
Platform: OS Independent
Classifier: Development Status :: 4 - Beta
Classifier: Framework :: Django
Classifier: Intended Audience :: Developers
Classifier: License :: OSI Approved :: BSD License
Classifier: Operating System :: OS Independent
Classifier: Topic :: Internet :: WWW/HTTP
Classifier: Programming Language :: Python
Classifier: Programming Language :: Python :: 2
Classifier: Programming Language :: Python :: 2.7
Classifier: Programming Language :: Python :: 3
Classifier: Programming Language :: Python :: 3.4
Classifier: Programming Language :: Python :: 3.5
Classifier: Programming Language :: Python :: 3.6
